[
  {
    "__type__": "cc.Prefab",
    "_name": "AssociationRankRewardItem",
    "_objFlags": 0,
    "__editorExtras__": {},
    "_native": "",
    "data": {
      "__id__": 1
    },
    "optimizationPolicy": 0,
    "persistent": false
  },
  {
    "__type__": "cc.Node",
    "_name": "AssociationRankRewardItem",
    "_objFlags": 0,
    "__editorExtras__": {},
    "_parent": null,
    "_children": [
      {
        "__id__": 2
      },
      {
        "__id__": 12
      },
      {
        "__id__": 22
      },
      {
        "__id__": 32
      },
      {
        "__id__": 48
      }
    ],
    "_active": true,
    "_components": [
      {
        "__id__": 79
      },
      {
        "__id__": 81
      },
      {
        "__id__": 83
      }
    ],
    "_prefab": {
      "__id__": 85
    },
    "_lpos": {
      "__type__": "cc.Vec3",
      "x": 0,
      "y": 0,
      "z": 0
    },
    "_lrot": {
      "__type__": "cc.Quat",
      "x": 0,
      "y": 0,
      "z": 0,
      "w": 1
    },
    "_lscale": {
      "__type__": "cc.Vec3",
      "x": 1,
      "y": 1,
      "z": 1
    },
    "_mobility": 0,
    "_layer": 33554432,
    "_euler": {
      "__type__": "cc.Vec3",
      "x": 0,
      "y": 0,
      "z": 0
    },
    "_id": ""
  },
  {
    "__type__": "cc.Node",
    "_name": "no1_node",
    "_objFlags": 0,
    "__editorExtras__": {},
    "_parent": {
      "__id__": 1
    },
    "_children": [
      {
        "__id__": 3
      }
    ],
    "_active": true,
    "_components": [
      {
        "__id__": 9
      }
    ],
    "_prefab": {
      "__id__": 11
    },
    "_lpos": {
      "__type__": "cc.Vec3",
      "x": 0,
      "y": 0,
      "z": 0
    },
    "_lrot": {
      "__type__": "cc.Quat",
      "x": 0,
      "y": 0,
      "z": 0,
      "w": 1
    },
    "_lscale": {
      "__type__": "cc.Vec3",
      "x": 1,
      "y": 1,
      "z": 1
    },
    "_mobility": 0,
    "_layer": 33554432,
    "_euler": {
      "__type__": "cc.Vec3",
      "x": 0,
      "y": 0,
      "z": 0
    },
    "_id": ""
  },
  {
    "__type__": "cc.Node",
    "_name": "no1_img",
    "_objFlags": 0,
    "__editorExtras__": {},
    "_parent": {
      "__id__": 2
    },
    "_children": [],
    "_active": true,
    "_components": [
      {
        "__id__": 4
      },
      {
        "__id__": 6
      }
    ],
    "_prefab": {
      "__id__": 8
    },
    "_lpos": {
      "__type__": "cc.Vec3",
      "x": 0,
      "y": 0,
      "z": 0
    },
    "_lrot": {
      "__type__": "cc.Quat",
      "x": 0,
      "y": 0,
      "z": 0,
      "w": 1
    },
    "_lscale": {
      "__type__": "cc.Vec3",
      "x": 1,
      "y": 1,
      "z": 1
    },
    "_mobility": 0,
    "_layer": 33554432,
    "_euler": {
      "__type__": "cc.Vec3",
      "x": 0,
      "y": 0,
      "z": 0
    },
    "_id": ""
  },
  {
    "__type__": "cc.UITransform",
    "_name": "",
    "_objFlags": 0,
    "__editorExtras__": {},
    "node": {
      "__id__": 3
    },
    "_enabled": true,
    "__prefab": {
      "__id__": 5
    },
    "_contentSize": {
      "__type__": "cc.Size",
      "width": 600,
      "height": 92
    },
    "_anchorPoint": {
      "__type__": "cc.Vec2",
      "x": 0.5,
      "y": 0.5
    },
    "_id": ""
  },
  {
    "__type__": "cc.CompPrefabInfo",
    "fileId": "dcGtTkq95GCpFNFLPEo7o9"
  },
  {
    "__type__": "cc.Sprite",
    "_name": "",
    "_objFlags": 0,
    "__editorExtras__": {},
    "node": {
      "__id__": 3
    },
    "_enabled": true,
    "__prefab": {
      "__id__": 7
    },
    "_customMaterial": null,
    "_srcBlendFactor": 2,
    "_dstBlendFactor": 4,
    "_color": {
      "__type__": "cc.Color",
      "r": 255,
      "g": 255,
      "b": 255,
      "a": 255
    },
    "_spriteFrame": {
      "__uuid__": "39dc31d2-f2a1-43c3-b94f-aa6b2ec6a609@f9941",
      "__expectedType__": "cc.SpriteFrame"
    },
    "_type": 1,
    "_fillType": 0,
    "_sizeMode": 0,
    "_fillCenter": {
      "__type__": "cc.Vec2",
      "x": 0,
      "y": 0
    },
    "_fillStart": 0,
    "_fillRange": 0,
    "_isTrimmedMode": false,
    "_useGrayscale": false,
    "_atlas": null,
    "_id": ""
  },
  {
    "__type__": "cc.CompPrefabInfo",
    "fileId": "0eVj3u0EJL1pXXBQ0DvOft"
  },
  {
    "__type__": "cc.PrefabInfo",
    "root": {
      "__id__": 1
    },
    "asset": {
      "__id__": 0
    },
    "fileId": "67FXALUbxHOIEUDujp8/eA",
    "instance": null,
    "targetOverrides": null,
    "nestedPrefabInstanceRoots": null
  },
  {
    "__type__": "cc.UITransform",
    "_name": "",
    "_objFlags": 0,
    "__editorExtras__": {},
    "node": {
      "__id__": 2
    },
    "_enabled": true,
    "__prefab": {
      "__id__": 10
    },
    "_contentSize": {
      "__type__": "cc.Size",
      "width": 100,
      "height": 100
    },
    "_anchorPoint": {
      "__type__": "cc.Vec2",
      "x": 0.5,
      "y": 0.5
    },
    "_id": ""
  },
  {
    "__type__": "cc.CompPrefabInfo",
    "fileId": "48WYGFI8lPVJ44w96HZyV5"
  },
  {
    "__type__": "cc.PrefabInfo",
    "root": {
      "__id__": 1
    },
    "asset": {
      "__id__": 0
    },
    "fileId": "74p41AXihAU44CzxLx1zPA",
    "instance": null,
    "targetOverrides": null,
    "nestedPrefabInstanceRoots": null
  },
  {
    "__type__": "cc.Node",
    "_name": "no2_node",
    "_objFlags": 0,
    "__editorExtras__": {},
    "_parent": {
      "__id__": 1
    },
    "_children": [
      {
        "__id__": 13
      }
    ],
    "_active": true,
    "_components": [
      {
        "__id__": 19
      }
    ],
    "_prefab": {
      "__id__": 21
    },
    "_lpos": {
      "__type__": "cc.Vec3",
      "x": 0,
      "y": 0,
      "z": 0
    },
    "_lrot": {
      "__type__": "cc.Quat",
      "x": 0,
      "y": 0,
      "z": 0,
      "w": 1
    },
    "_lscale": {
      "__type__": "cc.Vec3",
      "x": 1,
      "y": 1,
      "z": 1
    },
    "_mobility": 0,
    "_layer": 33554432,
    "_euler": {
      "__type__": "cc.Vec3",
      "x": 0,
      "y": 0,
      "z": 0
    },
    "_id": ""
  },
  {
    "__type__": "cc.Node",
    "_name": "no2_img",
    "_objFlags": 0,
    "__editorExtras__": {},
    "_parent": {
      "__id__": 12
    },
    "_children": [],
    "_active": true,
    "_components": [
      {
        "__id__": 14
      },
      {
        "__id__": 16
      }
    ],
    "_prefab": {
      "__id__": 18
    },
    "_lpos": {
      "__type__": "cc.Vec3",
      "x": 0,
      "y": 0,
      "z": 0
    },
    "_lrot": {
      "__type__": "cc.Quat",
      "x": 0,
      "y": 0,
      "z": 0,
      "w": 1
    },
    "_lscale": {
      "__type__": "cc.Vec3",
      "x": 1,
      "y": 1,
      "z": 1
    },
    "_mobility": 0,
    "_layer": 33554432,
    "_euler": {
      "__type__": "cc.Vec3",
      "x": 0,
      "y": 0,
      "z": 0
    },
    "_id": ""
  },
  {
    "__type__": "cc.UITransform",
    "_name": "",
    "_objFlags": 0,
    "__editorExtras__": {},
    "node": {
      "__id__": 13
    },
    "_enabled": true,
    "__prefab": {
      "__id__": 15
    },
    "_contentSize": {
      "__type__": "cc.Size",
      "width": 600,
      "height": 92
    },
    "_anchorPoint": {
      "__type__": "cc.Vec2",
      "x": 0.5,
      "y": 0.5
    },
    "_id": ""
  },
  {
    "__type__": "cc.CompPrefabInfo",
    "fileId": "d38JfGnQtLcIXVTonECc9V"
  },
  {
    "__type__": "cc.Sprite",
    "_name": "",
    "_objFlags": 0,
    "__editorExtras__": {},
    "node": {
      "__id__": 13
    },
    "_enabled": true,
    "__prefab": {
      "__id__": 17
    },
    "_customMaterial": null,
    "_srcBlendFactor": 2,
    "_dstBlendFactor": 4,
    "_color": {
      "__type__": "cc.Color",
      "r": 255,
      "g": 255,
      "b": 255,
      "a": 255
    },
    "_spriteFrame": {
      "__uuid__": "ad340489-43c2-4c4e-ab38-b5e36b520d24@f9941",
      "__expectedType__": "cc.SpriteFrame"
    },
    "_type": 1,
    "_fillType": 0,
    "_sizeMode": 0,
    "_fillCenter": {
      "__type__": "cc.Vec2",
      "x": 0,
      "y": 0
    },
    "_fillStart": 0,
    "_fillRange": 0,
    "_isTrimmedMode": true,
    "_useGrayscale": false,
    "_atlas": null,
    "_id": ""
  },
  {
    "__type__": "cc.CompPrefabInfo",
    "fileId": "2dTx5n0KZBMZ2oOkjlOxg3"
  },
  {
    "__type__": "cc.PrefabInfo",
    "root": {
      "__id__": 1
    },
    "asset": {
      "__id__": 0
    },
    "fileId": "00vXOOUWNCPoMCcBGfWCWJ",
    "instance": null,
    "targetOverrides": null,
    "nestedPrefabInstanceRoots": null
  },
  {
    "__type__": "cc.UITransform",
    "_name": "",
    "_objFlags": 0,
    "__editorExtras__": {},
    "node": {
      "__id__": 12
    },
    "_enabled": true,
    "__prefab": {
      "__id__": 20
    },
    "_contentSize": {
      "__type__": "cc.Size",
      "width": 100,
      "height": 100
    },
    "_anchorPoint": {
      "__type__": "cc.Vec2",
      "x": 0.5,
      "y": 0.5
    },
    "_id": ""
  },
  {
    "__type__": "cc.CompPrefabInfo",
    "fileId": "0frCY7V+RPpbWhA5PUZHKF"
  },
  {
    "__type__": "cc.PrefabInfo",
    "root": {
      "__id__": 1
    },
    "asset": {
      "__id__": 0
    },
    "fileId": "ba6MIhXQtKfKSJWXdY9oxZ",
    "instance": null,
    "targetOverrides": null,
    "nestedPrefabInstanceRoots": null
  },
  {
    "__type__": "cc.Node",
    "_name": "no3_node",
    "_objFlags": 0,
    "__editorExtras__": {},
    "_parent": {
      "__id__": 1
    },
    "_children": [
      {
        "__id__": 23
      }
    ],
    "_active": true,
    "_components": [
      {
        "__id__": 29
      }
    ],
    "_prefab": {
      "__id__": 31
    },
    "_lpos": {
      "__type__": "cc.Vec3",
      "x": 0,
      "y": 0,
      "z": 0
    },
    "_lrot": {
      "__type__": "cc.Quat",
      "x": 0,
      "y": 0,
      "z": 0,
      "w": 1
    },
    "_lscale": {
      "__type__": "cc.Vec3",
      "x": 1,
      "y": 1,
      "z": 1
    },
    "_mobility": 0,
    "_layer": 33554432,
    "_euler": {
      "__type__": "cc.Vec3",
      "x": 0,
      "y": 0,
      "z": 0
    },
    "_id": ""
  },
  {
    "__type__": "cc.Node",
    "_name": "no3_img",
    "_objFlags": 0,
    "__editorExtras__": {},
    "_parent": {
      "__id__": 22
    },
    "_children": [],
    "_active": true,
    "_components": [
      {
        "__id__": 24
      },
      {
        "__id__": 26
      }
    ],
    "_prefab": {
      "__id__": 28
    },
    "_lpos": {
      "__type__": "cc.Vec3",
      "x": 0,
      "y": 0,
      "z": 0
    },
    "_lrot": {
      "__type__": "cc.Quat",
      "x": 0,
      "y": 0,
      "z": 0,
      "w": 1
    },
    "_lscale": {
      "__type__": "cc.Vec3",
      "x": 1,
      "y": 1,
      "z": 1
    },
    "_mobility": 0,
    "_layer": 33554432,
    "_euler": {
      "__type__": "cc.Vec3",
      "x": 0,
      "y": 0,
      "z": 0
    },
    "_id": ""
  },
  {
    "__type__": "cc.UITransform",
    "_name": "",
    "_objFlags": 0,
    "__editorExtras__": {},
    "node": {
      "__id__": 23
    },
    "_enabled": true,
    "__prefab": {
      "__id__": 25
    },
    "_contentSize": {
      "__type__": "cc.Size",
      "width": 600,
      "height": 92
    },
    "_anchorPoint": {
      "__type__": "cc.Vec2",
      "x": 0.5,
      "y": 0.5
    },
    "_id": ""
  },
  {
    "__type__": "cc.CompPrefabInfo",
    "fileId": "10mr7F1VlH6bazWUbCXecz"
  },
  {
    "__type__": "cc.Sprite",
    "_name": "",
    "_objFlags": 0,
    "__editorExtras__": {},
    "node": {
      "__id__": 23
    },
    "_enabled": true,
    "__prefab": {
      "__id__": 27
    },
    "_customMaterial": null,
    "_srcBlendFactor": 2,
    "_dstBlendFactor": 4,
    "_color": {
      "__type__": "cc.Color",
      "r": 255,
      "g": 255,
      "b": 255,
      "a": 255
    },
    "_spriteFrame": {
      "__uuid__": "aa3246ea-589a-455e-aae3-3db8e5647719@f9941",
      "__expectedType__": "cc.SpriteFrame"
    },
    "_type": 1,
    "_fillType": 0,
    "_sizeMode": 0,
    "_fillCenter": {
      "__type__": "cc.Vec2",
      "x": 0,
      "y": 0
    },
    "_fillStart": 0,
    "_fillRange": 0,
    "_isTrimmedMode": true,
    "_useGrayscale": false,
    "_atlas": null,
    "_id": ""
  },
  {
    "__type__": "cc.CompPrefabInfo",
    "fileId": "c4uMUCCmhIYIqr9J3bVLaA"
  },
  {
    "__type__": "cc.PrefabInfo",
    "root": {
      "__id__": 1
    },
    "asset": {
      "__id__": 0
    },
    "fileId": "c91If9L7BOK6ILkvic6IW+",
    "instance": null,
    "targetOverrides": null,
    "nestedPrefabInstanceRoots": null
  },
  {
    "__type__": "cc.UITransform",
    "_name": "",
    "_objFlags": 0,
    "__editorExtras__": {},
    "node": {
      "__id__": 22
    },
    "_enabled": true,
    "__prefab": {
      "__id__": 30
    },
    "_contentSize": {
      "__type__": "cc.Size",
      "width": 100,
      "height": 100
    },
    "_anchorPoint": {
      "__type__": "cc.Vec2",
      "x": 0.5,
      "y": 0.5
    },
    "_id": ""
  },
  {
    "__type__": "cc.CompPrefabInfo",
    "fileId": "1fjDp4XDNDj6KNbEiE7Y/n"
  },
  {
    "__type__": "cc.PrefabInfo",
    "root": {
      "__id__": 1
    },
    "asset": {
      "__id__": 0
    },
    "fileId": "cdUeUMW0pGWZ6L3CQ0q1hS",
    "instance": null,
    "targetOverrides": null,
    "nestedPrefabInstanceRoots": null
  },
  {
    "__type__": "cc.Node",
    "_name": "qiTaiPaiMing_node",
    "_objFlags": 0,
    "__editorExtras__": {},
    "_parent": {
      "__id__": 1
    },
    "_children": [
      {
        "__id__": 33
      },
      {
        "__id__": 39
      }
    ],
    "_active": true,
    "_components": [
      {
        "__id__": 45
      }
    ],
    "_prefab": {
      "__id__": 47
    },
    "_lpos": {
      "__type__": "cc.Vec3",
      "x": 0,
      "y": 0,
      "z": 0
    },
    "_lrot": {
      "__type__": "cc.Quat",
      "x": 0,
      "y": 0,
      "z": 0,
      "w": 1
    },
    "_lscale": {
      "__type__": "cc.Vec3",
      "x": 1,
      "y": 1,
      "z": 1
    },
    "_mobility": 0,
    "_layer": 33554432,
    "_euler": {
      "__type__": "cc.Vec3",
      "x": 0,
      "y": 0,
      "z": 0
    },
    "_id": ""
  },
  {
    "__type__": "cc.Node",
    "_name": "qiTaiPaiMing_img",
    "_objFlags": 0,
    "__editorExtras__": {},
    "_parent": {
      "__id__": 32
    },
    "_children": [],
    "_active": true,
    "_components": [
      {
        "__id__": 34
      },
      {
        "__id__": 36
      }
    ],
    "_prefab": {
      "__id__": 38
    },
    "_lpos": {
      "__type__": "cc.Vec3",
      "x": 0,
      "y": 0,
      "z": 0
    },
    "_lrot": {
      "__type__": "cc.Quat",
      "x": 0,
      "y": 0,
      "z": 0,
      "w": 1
    },
    "_lscale": {
      "__type__": "cc.Vec3",
      "x": 1,
      "y": 1,
      "z": 1
    },
    "_mobility": 0,
    "_layer": 33554432,
    "_euler": {
      "__type__": "cc.Vec3",
      "x": 0,
      "y": 0,
      "z": 0
    },
    "_id": ""
  },
  {
    "__type__": "cc.UITransform",
    "_name": "",
    "_objFlags": 0,
    "__editorExtras__": {},
    "node": {
      "__id__": 33
    },
    "_enabled": true,
    "__prefab": {
      "__id__": 35
    },
    "_contentSize": {
      "__type__": "cc.Size",
      "width": 600,
      "height": 92
    },
    "_anchorPoint": {
      "__type__": "cc.Vec2",
      "x": 0.5,
      "y": 0.5
    },
    "_id": ""
  },
  {
    "__type__": "cc.CompPrefabInfo",
    "fileId": "32vtm/ldJLQbrd3oO3uQmD"
  },
  {
    "__type__": "cc.Sprite",
    "_name": "",
    "_objFlags": 0,
    "__editorExtras__": {},
    "node": {
      "__id__": 33
    },
    "_enabled": true,
    "__prefab": {
      "__id__": 37
    },
    "_customMaterial": null,
    "_srcBlendFactor": 2,
    "_dstBlendFactor": 4,
    "_color": {
      "__type__": "cc.Color",
      "r": 255,
      "g": 255,
      "b": 255,
      "a": 255
    },
    "_spriteFrame": {
      "__uuid__": "a387ddf7-c14e-490d-92d7-9c1467cf0bfb@f9941",
      "__expectedType__": "cc.SpriteFrame"
    },
    "_type": 1,
    "_fillType": 0,
    "_sizeMode": 0,
    "_fillCenter": {
      "__type__": "cc.Vec2",
      "x": 0,
      "y": 0
    },
    "_fillStart": 0,
    "_fillRange": 0,
    "_isTrimmedMode": true,
    "_useGrayscale": false,
    "_atlas": null,
    "_id": ""
  },
  {
    "__type__": "cc.CompPrefabInfo",
    "fileId": "120v9H0AVOJYOCZJPf1HnE"
  },
  {
    "__type__": "cc.PrefabInfo",
    "root": {
      "__id__": 1
    },
    "asset": {
      "__id__": 0
    },
    "fileId": "726pQR2kpFL4FrqSaRXs5G",
    "instance": null,
    "targetOverrides": null,
    "nestedPrefabInstanceRoots": null
  },
  {
    "__type__": "cc.Node",
    "_name": "rankmun_txt",
    "_objFlags": 0,
    "__editorExtras__": {},
    "_parent": {
      "__id__": 32
    },
    "_children": [],
    "_active": true,
    "_components": [
      {
        "__id__": 40
      },
      {
        "__id__": 42
      }
    ],
    "_prefab": {
      "__id__": 44
    },
    "_lpos": {
      "__type__": "cc.Vec3",
      "x": -235,
      "y": 0,
      "z": 0
    },
    "_lrot": {
      "__type__": "cc.Quat",
      "x": 0,
      "y": 0,
      "z": 0,
      "w": 1
    },
    "_lscale": {
      "__type__": "cc.Vec3",
      "x": 1,
      "y": 1,
      "z": 1
    },
    "_mobility": 0,
    "_layer": 33554432,
    "_euler": {
      "__type__": "cc.Vec3",
      "x": 0,
      "y": 0,
      "z": 0
    },
    "_id": ""
  },
  {
    "__type__": "cc.UITransform",
    "_name": "",
    "_objFlags": 0,
    "__editorExtras__": {},
    "node": {
      "__id__": 39
    },
    "_enabled": true,
    "__prefab": {
      "__id__": 41
    },
    "_contentSize": {
      "__type__": "cc.Size",
      "width": 120,
      "height": 54.400000000000006
    },
    "_anchorPoint": {
      "__type__": "cc.Vec2",
      "x": 0.5,
      "y": 0.5
    },
    "_id": ""
  },
  {
    "__type__": "cc.CompPrefabInfo",
    "fileId": "429MA9YlJMfr22ZUjatexe"
  },
  {
    "__type__": "cc.Label",
    "_name": "",
    "_objFlags": 0,
    "__editorExtras__": {},
    "node": {
      "__id__": 39
    },
    "_enabled": true,
    "__prefab": {
      "__id__": 43
    },
    "_customMaterial": null,
    "_srcBlendFactor": 2,
    "_dstBlendFactor": 4,
    "_color": {
      "__type__": "cc.Color",
      "r": 255,
      "g": 255,
      "b": 255,
      "a": 255
    },
    "_string": "4",
    "_horizontalAlign": 1,
    "_verticalAlign": 1,
    "_actualFontSize": 34,
    "_fontSize": 32,
    "_fontFamily": "Arial",
    "_lineHeight": 32,
    "_overflow": 2,
    "_enableWrapText": false,
    "_font": null,
    "_isSystemFontUsed": true,
    "_spacingX": 0,
    "_isItalic": false,
    "_isBold": true,
    "_isUnderline": false,
    "_underlineHeight": 2,
    "_cacheMode": 0,
    "_enableOutline": true,
    "_outlineColor": {
      "__type__": "cc.Color",
      "r": 0,
      "g": 0,
      "b": 0,
      "a": 255
    },
    "_outlineWidth": 3,
    "_enableShadow": false,
    "_shadowColor": {
      "__type__": "cc.Color",
      "r": 0,
      "g": 0,
      "b": 0,
      "a": 255
    },
    "_shadowOffset": {
      "__type__": "cc.Vec2",
      "x": 2,
      "y": 2
    },
    "_shadowBlur": 2,
    "_id": ""
  },
  {
    "__type__": "cc.CompPrefabInfo",
    "fileId": "39n0yTZ1hBnoHqSnPhO8/H"
  },
  {
    "__type__": "cc.PrefabInfo",
    "root": {
      "__id__": 1
    },
    "asset": {
      "__id__": 0
    },
    "fileId": "65XFP/O8NP85/cnDFbIvXw",
    "instance": null,
    "targetOverrides": null,
    "nestedPrefabInstanceRoots": null
  },
  {
    "__type__": "cc.UITransform",
    "_name": "",
    "_objFlags": 0,
    "__editorExtras__": {},
    "node": {
      "__id__": 32
    },
    "_enabled": true,
    "__prefab": {
      "__id__": 46
    },
    "_contentSize": {
      "__type__": "cc.Size",
      "width": 100,
      "height": 100
    },
    "_anchorPoint": {
      "__type__": "cc.Vec2",
      "x": 0.5,
      "y": 0.5
    },
    "_id": ""
  },
  {
    "__type__": "cc.CompPrefabInfo",
    "fileId": "3e4uuvsW5N86kJDv5ocMNi"
  },
  {
    "__type__": "cc.PrefabInfo",
    "root": {
      "__id__": 1
    },
    "asset": {
      "__id__": 0
    },
    "fileId": "b2rkXfVSBJrIHdlGOMQe1k",
    "instance": null,
    "targetOverrides": null,
    "nestedPrefabInstanceRoots": null
  },
  {
    "__type__": "cc.Node",
    "_name": "private_node",
    "_objFlags": 0,
    "__editorExtras__": {},
    "_parent": {
      "__id__": 1
    },
    "_children": [
      {
        "__id__": 49
      },
      {
        "__id__": 64
      },
      {
        "__id__": 70
      }
    ],
    "_active": true,
    "_components": [
      {
        "__id__": 76
      }
    ],
    "_prefab": {
      "__id__": 78
    },
    "_lpos": {
      "__type__": "cc.Vec3",
      "x": -60,
      "y": 0,
      "z": 0
    },
    "_lrot": {
      "__type__": "cc.Quat",
      "x": 0,
      "y": 0,
      "z": 0,
      "w": 1
    },
    "_lscale": {
      "__type__": "cc.Vec3",
      "x": 1,
      "y": 1,
      "z": 1
    },
    "_mobility": 0,
    "_layer": 33554432,
    "_euler": {
      "__type__": "cc.Vec3",
      "x": 0,
      "y": 0,
      "z": 0
    },
    "_id": ""
  },
  {
    "__type__": "cc.Node",
    "_objFlags": 0,
    "_parent": {
      "__id__": 48
    },
    "_prefab": {
      "__id__": 50
    },
    "__editorExtras__": {}
  },
  {
    "__type__": "cc.PrefabInfo",
    "root": {
      "__id__": 49
    },
    "asset": {
      "__uuid__": "2200b2f1-18d2-407a-836b-b7972f2701f0",
      "__expectedType__": "cc.Prefab"
    },
    "fileId": "089iONcttCab8MDFvCGGyM",
    "instance": {
      "__id__": 51
    },
    "targetOverrides": null
  },
  {
    "__type__": "cc.PrefabInstance",
    "fileId": "eeLfGBI/lH3LJZ40oZQK+s",
    "prefabRootNode": {
      "__id__": 1
    },
    "mountedChildren": [],
    "mountedComponents": [],
    "propertyOverrides": [
      {
        "__id__": 52
      },
      {
        "__id__": 54
      },
      {
        "__id__": 56
      },
      {
        "__id__": 58
      },
      {
        "__id__": 60
      },
      {
        "__id__": 62
      }
    ],
    "removedComponents": []
  },
  {
    "__type__": "CCPropertyOverrideInfo",
    "targetInfo": {
      "__id__": 53
    },
    "propertyPath": [
      "_name"
    ],
    "value": "PlayerHeadItem"
  },
  {
    "__type__": "cc.TargetInfo",
    "localID": [
      "089iONcttCab8MDFvCGGyM"
    ]
  },
  {
    "__type__": "CCPropertyOverrideInfo",
    "targetInfo": {
      "__id__": 55
    },
    "propertyPath": [
      "_lpos"
    ],
    "value": {
      "__type__": "cc.Vec3",
      "x": -40,
      "y": 0,
      "z": 0
    }
  },
  {
    "__type__": "cc.TargetInfo",
    "localID": [
      "089iONcttCab8MDFvCGGyM"
    ]
  },
  {
    "__type__": "CCPropertyOverrideInfo",
    "targetInfo": {
      "__id__": 57
    },
    "propertyPath": [
      "_lrot"
    ],
    "value": {
      "__type__": "cc.Quat",
      "x": 0,
      "y": 0,
      "z": 0,
      "w": 1
    }
  },
  {
    "__type__": "cc.TargetInfo",
    "localID": [
      "089iONcttCab8MDFvCGGyM"
    ]
  },
  {
    "__type__": "CCPropertyOverrideInfo",
    "targetInfo": {
      "__id__": 59
    },
    "propertyPath": [
      "_euler"
    ],
    "value": {
      "__type__": "cc.Vec3",
      "x": 0,
      "y": 0,
      "z": 0
    }
  },
  {
    "__type__": "cc.TargetInfo",
    "localID": [
      "089iONcttCab8MDFvCGGyM"
    ]
  },
  {
    "__type__": "CCPropertyOverrideInfo",
    "targetInfo": {
      "__id__": 61
    },
    "propertyPath": [
      "_contentSize"
    ],
    "value": {
      "__type__": "cc.Size",
      "width": 15.118718712075243,
      "height": 29.2
    }
  },
  {
    "__type__": "cc.TargetInfo",
    "localID": [
      "7bynQhRopJ5rS5J5wCO96m"
    ]
  },
  {
    "__type__": "CCPropertyOverrideInfo",
    "targetInfo": {
      "__id__": 63
    },
    "propertyPath": [
      "_lscale"
    ],
    "value": {
      "__type__": "cc.Vec3",
      "x": 0.8,
      "y": 0.8,
      "z": 1
    }
  },
  {
    "__type__": "cc.TargetInfo",
    "localID": [
      "089iONcttCab8MDFvCGGyM"
    ]
  },
  {
    "__type__": "cc.Node",
    "_name": "name_txt",
    "_objFlags": 0,
    "__editorExtras__": {},
    "_parent": {
      "__id__": 48
    },
    "_children": [],
    "_active": true,
    "_components": [
      {
        "__id__": 65
      },
      {
        "__id__": 67
      }
    ],
    "_prefab": {
      "__id__": 69
    },
    "_lpos": {
      "__type__": "cc.Vec3",
      "x": 10,
      "y": 0,
      "z": 0
    },
    "_lrot": {
      "__type__": "cc.Quat",
      "x": 0,
      "y": 0,
      "z": 0,
      "w": 1
    },
    "_lscale": {
      "__type__": "cc.Vec3",
      "x": 1,
      "y": 1,
      "z": 1
    },
    "_mobility": 0,
    "_layer": 33554432,
    "_euler": {
      "__type__": "cc.Vec3",
      "x": 0,
      "y": 0,
      "z": 0
    },
    "_id": ""
  },
  {
    "__type__": "cc.UITransform",
    "_name": "",
    "_objFlags": 0,
    "__editorExtras__": {},
    "node": {
      "__id__": 64
    },
    "_enabled": true,
    "__prefab": {
      "__id__": 66
    },
    "_contentSize": {
      "__type__": "cc.Size",
      "width": 250,
      "height": 54.4
    },
    "_anchorPoint": {
      "__type__": "cc.Vec2",
      "x": 0,
      "y": 0.5
    },
    "_id": ""
  },
  {
    "__type__": "cc.CompPrefabInfo",
    "fileId": "1agP3kKyVH0pSr1ngtv8dP"
  },
  {
    "__type__": "cc.Label",
    "_name": "",
    "_objFlags": 0,
    "__editorExtras__": {},
    "node": {
      "__id__": 64
    },
    "_enabled": true,
    "__prefab": {
      "__id__": 68
    },
    "_customMaterial": null,
    "_srcBlendFactor": 2,
    "_dstBlendFactor": 4,
    "_color": {
      "__type__": "cc.Color",
      "r": 255,
      "g": 255,
      "b": 255,
      "a": 255
    },
    "_string": "player name",
    "_horizontalAlign": 0,
    "_verticalAlign": 1,
    "_actualFontSize": 25,
    "_fontSize": 24,
    "_fontFamily": "Arial",
    "_lineHeight": 40,
    "_overflow": 2,
    "_enableWrapText": false,
    "_font": null,
    "_isSystemFontUsed": true,
    "_spacingX": 0,
    "_isItalic": false,
    "_isBold": true,
    "_isUnderline": false,
    "_underlineHeight": 2,
    "_cacheMode": 0,
    "_enableOutline": true,
    "_outlineColor": {
      "__type__": "cc.Color",
      "r": 0,
      "g": 0,
      "b": 0,
      "a": 255
    },
    "_outlineWidth": 2,
    "_enableShadow": false,
    "_shadowColor": {
      "__type__": "cc.Color",
      "r": 0,
      "g": 0,
      "b": 0,
      "a": 255
    },
    "_shadowOffset": {
      "__type__": "cc.Vec2",
      "x": 2,
      "y": 2
    },
    "_shadowBlur": 2,
    "_id": ""
  },
  {
    "__type__": "cc.CompPrefabInfo",
    "fileId": "e3VOf+lING7I6CjprC8+ze"
  },
  {
    "__type__": "cc.PrefabInfo",
    "root": {
      "__id__": 1
    },
    "asset": {
      "__id__": 0
    },
    "fileId": "cbesSQ0jZD2aFe7hAt3AJI",
    "instance": null,
    "targetOverrides": null,
    "nestedPrefabInstanceRoots": null
  },
  {
    "__type__": "cc.Node",
    "_name": "damage_txt",
    "_objFlags": 0,
    "__editorExtras__": {},
    "_parent": {
      "__id__": 48
    },
    "_children": [],
    "_active": true,
    "_components": [
      {
        "__id__": 71
      },
      {
        "__id__": 73
      }
    ],
    "_prefab": {
      "__id__": 75
    },
    "_lpos": {
      "__type__": "cc.Vec3",
      "x": 300,
      "y": 0,
      "z": 0
    },
    "_lrot": {
      "__type__": "cc.Quat",
      "x": 0,
      "y": 0,
      "z": 0,
      "w": 1
    },
    "_lscale": {
      "__type__": "cc.Vec3",
      "x": 1,
      "y": 1,
      "z": 1
    },
    "_mobility": 0,
    "_layer": 33554432,
    "_euler": {
      "__type__": "cc.Vec3",
      "x": 0,
      "y": 0,
      "z": 0
    },
    "_id": ""
  },
  {
    "__type__": "cc.UITransform",
    "_name": "",
    "_objFlags": 0,
    "__editorExtras__": {},
    "node": {
      "__id__": 70
    },
    "_enabled": true,
    "__prefab": {
      "__id__": 72
    },
    "_contentSize": {
      "__type__": "cc.Size",
      "width": 77.3828125,
      "height": 54.4
    },
    "_anchorPoint": {
      "__type__": "cc.Vec2",
      "x": 0.5,
      "y": 0.5
    },
    "_id": ""
  },
  {
    "__type__": "cc.CompPrefabInfo",
    "fileId": "a8NyWUylZD6Lb7jqBtYyng"
  },
  {
    "__type__": "cc.Label",
    "_name": "",
    "_objFlags": 0,
    "__editorExtras__": {},
    "node": {
      "__id__": 70
    },
    "_enabled": true,
    "__prefab": {
      "__id__": 74
    },
    "_customMaterial": null,
    "_srcBlendFactor": 2,
    "_dstBlendFactor": 4,
    "_color": {
      "__type__": "cc.Color",
      "r": 255,
      "g": 255,
      "b": 255,
      "a": 255
    },
    "_string": "1500M",
    "_horizontalAlign": 1,
    "_verticalAlign": 1,
    "_actualFontSize": 25.75,
    "_fontSize": 24,
    "_fontFamily": "Arial",
    "_lineHeight": 40,
    "_overflow": 0,
    "_enableWrapText": false,
    "_font": null,
    "_isSystemFontUsed": true,
    "_spacingX": 0,
    "_isItalic": false,
    "_isBold": true,
    "_isUnderline": false,
    "_underlineHeight": 2,
    "_cacheMode": 0,
    "_enableOutline": true,
    "_outlineColor": {
      "__type__": "cc.Color",
      "r": 0,
      "g": 0,
      "b": 0,
      "a": 255
    },
    "_outlineWidth": 2,
    "_enableShadow": false,
    "_shadowColor": {
      "__type__": "cc.Color",
      "r": 0,
      "g": 0,
      "b": 0,
      "a": 255
    },
    "_shadowOffset": {
      "__type__": "cc.Vec2",
      "x": 2,
      "y": 2
    },
    "_shadowBlur": 2,
    "_id": ""
  },
  {
    "__type__": "cc.CompPrefabInfo",
    "fileId": "36z88zuNxDD6CXaJzrxm9c"
  },
  {
    "__type__": "cc.PrefabInfo",
    "root": {
      "__id__": 1
    },
    "asset": {
      "__id__": 0
    },
    "fileId": "d9U5VXohZLTY+NfXhF/BXx",
    "instance": null,
    "targetOverrides": null,
    "nestedPrefabInstanceRoots": null
  },
  {
    "__type__": "cc.UITransform",
    "_name": "",
    "_objFlags": 0,
    "__editorExtras__": {},
    "node": {
      "__id__": 48
    },
    "_enabled": true,
    "__prefab": {
      "__id__": 77
    },
    "_contentSize": {
      "__type__": "cc.Size",
      "width": 100,
      "height": 100
    },
    "_anchorPoint": {
      "__type__": "cc.Vec2",
      "x": 0.5,
      "y": 0.5
    },
    "_id": ""
  },
  {
    "__type__": "cc.CompPrefabInfo",
    "fileId": "6fEaYYzwFEYLwgFKqQYf14"
  },
  {
    "__type__": "cc.PrefabInfo",
    "root": {
      "__id__": 1
    },
    "asset": {
      "__id__": 0
    },
    "fileId": "9d79wk/U5OwK8nXcnxa8ek",
    "instance": null,
    "targetOverrides": null,
    "nestedPrefabInstanceRoots": null
  },
  {
    "__type__": "cc.UITransform",
    "_name": "",
    "_objFlags": 0,
    "__editorExtras__": {},
    "node": {
      "__id__": 1
    },
    "_enabled": true,
    "__prefab": {
      "__id__": 80
    },
    "_contentSize": {
      "__type__": "cc.Size",
      "width": 100,
      "height": 100
    },
    "_anchorPoint": {
      "__type__": "cc.Vec2",
      "x": 0.5,
      "y": 0.5
    },
    "_id": ""
  },
  {
    "__type__": "cc.CompPrefabInfo",
    "fileId": "87+y8vqIdC2rAatfoKjU6x"
  },
  {
    "__type__": "cc.Widget",
    "_name": "",
    "_objFlags": 0,
    "__editorExtras__": {},
    "node": {
      "__id__": 1
    },
    "_enabled": true,
    "__prefab": {
      "__id__": 82
    },
    "_alignFlags": 0,
    "_target": null,
    "_left": 0,
    "_right": 0,
    "_top": 0,
    "_bottom": 0,
    "_horizontalCenter": 0,
    "_verticalCenter": 0,
    "_isAbsLeft": true,
    "_isAbsRight": true,
    "_isAbsTop": true,
    "_isAbsBottom": true,
    "_isAbsHorizontalCenter": true,
    "_isAbsVerticalCenter": true,
    "_originalWidth": 0,
    "_originalHeight": 0,
    "_alignMode": 2,
    "_lockFlags": 0,
    "_id": ""
  },
  {
    "__type__": "cc.CompPrefabInfo",
    "fileId": "8fu2gS8/pK4ZgZTllAFb79"
  },
  {
    "__type__": "afc33fEuuNG07+UXRoDUNWs",
    "_name": "",
    "_objFlags": 0,
    "__editorExtras__": {},
    "node": {
      "__id__": 1
    },
    "_enabled": true,
    "__prefab": {
      "__id__": 84
    },
    "no1_Node": {
      "__id__": 2
    },
    "no2_Node": {
      "__id__": 12
    },
    "no3_Node": {
      "__id__": 22
    },
    "qiTaiNode": {
      "__id__": 32
    },
    "rewardLayout": null,
    "rankNunLab": {
      "__id__": 42
    },
    "_id": ""
  },
  {
    "__type__": "cc.CompPrefabInfo",
    "fileId": "71ddVpA5tITro2C/YelVOp"
  },
  {
    "__type__": "cc.PrefabInfo",
    "root": {
      "__id__": 1
    },
    "asset": {
      "__id__": 0
    },
    "fileId": "c46/YsCPVOJYA4mWEpNYRx",
    "instance": null,
    "targetOverrides": null,
    "nestedPrefabInstanceRoots": [
      {
        "__id__": 49
      }
    ]
  }
]