{
  "__version__": "1.0.1",
  "builder": {
    "taskOptionsMap": {
      "1709190642822": {
        "defaultLanguage": "zh-Hans-CN",
        "targetLanguageMap": {
          "zh-Hans-CN": {
            "locale": "zh-Hans-CN",
            "value": true
          }
        },
        "fallbackLanguage": "zh-Hans-CN"
      }
    },
    "__version__": "1.3.7",
    "options": {
      "wechatgame": {
        "defaultLanguage": "zh-Hans-CN",
        "targetLanguageMap": {
          "zh-Hans-CN": {
            "locale": "zh-Hans-CN",
            "value": true
          }
        },
        "fallbackLanguage": "zh-Hans-CN"
      }
    }
  }
}
