{
  "__type__": "cc.SpriteFrame",
  "content": {
    "name": "sc001_00004",
    "atlas": "30d05cc1-2fbc-4371-8311-04f1306d2698",
    "rect": {
      "x": 600,
      "y": 0,
      "width": 150,
      "height": 150
    },
    "offset": {
      "x": 0,
      "y": 0
    },
    "originalSize": {
      "width": 150,
      "height": 150
    },
    "rotated": false,
    "capInsets": [
      0,
      0,
      0,
      0
    ],
    "vertices": {
      "rawPosition": [],
      "indexes": [],
      "uv": [],
      "nuv": [],
      "minPos": {
        "x": 0,
        "y": 0,
        "z": 0
      },
      "maxPos": {
        "x": 0,
        "y": 0,
        "z": 0
      }
    },
    "texture": "b920424b-0618-4687-962b-52dbe04bc48d@6c48a",
    "packable": true,
    "pixelsToUnit": 100,
    "pivot": {
      "x": 0.5,
      "y": 0.5
    },
    "meshType": 0
  }
}