{
  "__type__": "cc.SpriteFrame",
  "content": {
    "name": "effect_hero_dxzs-effect_idle_11",
    "atlas": "966c9996-c245-4ebd-89a6-2dda058d1465",
    "rect": {
      "x": 0,
      "y": 1089,
      "width": 355,
      "height": 99
    },
    "offset": {
      "x": 0,
      "y": 0
    },
    "originalSize": {
      "width": 355,
      "height": 99
    },
    "rotated": false,
    "capInsets": [
      0,
      0,
      0,
      0
    ],
    "vertices": {
      "rawPosition": [],
      "indexes": [],
      "uv": [],
      "nuv": [],
      "minPos": {
        "x": 0,
        "y": 0,
        "z": 0
      },
      "maxPos": {
        "x": 0,
        "y": 0,
        "z": 0
      }
    },
    "texture": "14c294ff-a83c-4747-b2cd-0807e57f18dc@6c48a",
    "packable": true,
    "pixelsToUnit": 100,
    "pivot": {
      "x": 0.5,
      "y": 0.5
    },
    "meshType": 0
  }
}